fairscape_models/__init__.py
fairscape_models/base.py
fairscape_models/computation.py
fairscape_models/dataset.py
fairscape_models/ro_crate.py
fairscape_models/software.py
fairscape_models-1.3.0.dist-info/LICENSE
fairscape_models-1.3.0.dist-info/METADATA
fairscape_models-1.3.0.dist-info/WHEEL
fairscape_models-1.3.0.dist-info/top_level.txt
fairscape_models-1.3.0.dist-info/RECORD
