Metadata-Version: 2.1
Name: fairscape-models
Version: 1.3.0
Summary: Pydantic models for B2AI metadata validation
Author-email: Max Levinson <mal8ch@virginia.edu>
License: MIT License
Project-URL: Homepage, https://github.com/fairscape/fairscape-models
Keywords: fairscape,reproducibility,fair,b2ai
Classifier: License :: OSI Approved :: MIT License
Classifier: Programming Language :: Python
Classifier: Programming Language :: Python :: 3
Requires-Python: >=3.6
License-File: LICENSE
Requires-Dist: pydantic
